LICENSE
README.md
setup.py
chrom.egg-info/PKG-INFO
chrom.egg-info/SOURCES.txt
chrom.egg-info/dependency_links.txt
chrom.egg-info/top_level.txt
fortnite/__init__.py
fortnite/auth.py