Metadata-Version: 2.1
Name: chrom
Version: 0.0.1
Summary: Package for video game Fortnite
Home-page: https://fnbr.me/tutan
Author: Chrom
Author-email: chrom@fnbr.me
License: UNKNOWN
Platform: UNKNOWN
Classifier: Programming Language :: Python :: 3
Classifier: License :: OSI Approved :: MIT License
Classifier: Operating System :: OS Independent
Requires-Python: >=3.6
License-File: LICENSE
